setup.py
interval_set/__init__.py
interval_set/interval_set.py
interval_set.egg-info/PKG-INFO
interval_set.egg-info/SOURCES.txt
interval_set.egg-info/dependency_links.txt
interval_set.egg-info/not-zip-safe
interval_set.egg-info/top_level.txt