Metadata-Version: 1.0
Name: interval-set
Version: 1.1
Summary: Closed interval set toolkit for resources representation in scheduling
Home-page: https://github.com/oar-team/interval_set
Author: Michael Mercier
Author-email: michael.mercier@inria.fr
License: BSD
Platform: UNKNOWN
